{
  "hash": "979c6f5f",
  "configHash": "14e62625",
  "lockfileHash": "bb844114",
  "browserHash": "e0905092",
  "optimized": {
    "lucide-react": {
      "src": "../../lucide-react/dist/esm/lucide-react.js",
      "file": "lucide-react.js",
      "fileHash": "9c162b12",
      "needsInterop": false
    },
    "react-dom": {
      "src": "../../react-dom/index.js",
      "file": "react-dom.js",
      "fileHash": "ec151f20",
      "needsInterop": true
    },
    "react-dom/client": {
      "src": "../../react-dom/client.js",
      "file": "react-dom_client.js",
      "fileHash": "978911b4",
      "needsInterop": true
    },
    "react-router-dom": {
      "src": "../../react-router-dom/dist/index.mjs",
      "file": "react-router-dom.js",
      "fileHash": "69402623",
      "needsInterop": false
    },
    "react": {
      "src": "../../react/index.js",
      "file": "react.js",
      "fileHash": "f7bddf0f",
      "needsInterop": true
    },
    "react/jsx-dev-runtime": {
      "src": "../../react/jsx-dev-runtime.js",
      "file": "react_jsx-dev-runtime.js",
      "fileHash": "33d765e8",
      "needsInterop": true
    },
    "react/jsx-runtime": {
      "src": "../../react/jsx-runtime.js",
      "file": "react_jsx-runtime.js",
      "fileHash": "0e7d5136",
      "needsInterop": true
    }
  },
  "chunks": {
    "react-3_O8oni9": {
      "file": "react-3_O8oni9.js",
      "isDynamicEntry": false
    }
  }
}